nanotrace/__init__.py
nanotrace/abf.py
nanotrace/decorators.py
nanotrace/exception.py
nanotrace/experimental.py
nanotrace/features.py
nanotrace/learn.py
nanotrace/pipeline.py
nanotrace/plotting.py
nanotrace/segment.py
nanotrace/stages.py
nanotrace-1.0.3.dist-info/METADATA
nanotrace-1.0.3.dist-info/WHEEL
nanotrace-1.0.3.dist-info/licenses/LICENSE
nanotrace-1.0.3.dist-info/RECORD
