Metadata-Version: 2.4
Name: nanotrace
Version: 1.0.3
Summary: Automated nanopore electrophysiology (1d timeseries) manipulation and feature extraction.
Project-URL: Homepage, https://github.com/mjtadema/porepipe
Project-URL: Issues, https://github.com/mjtadema/porepipe/issues
Author-email: Matthijs Tadema <m.j.tadema@rug.nl>
License-Expression: Apache-2.0
License-File: LICENSE
Classifier: Operating System :: OS Independent
Classifier: Programming Language :: Python :: 3
Requires-Python: >=3.8
Requires-Dist: anytree
Requires-Dist: ipywidgets
Requires-Dist: joblib
Requires-Dist: matplotlib
Requires-Dist: numba
Requires-Dist: numpy
Requires-Dist: pandas
Requires-Dist: pyabf
Requires-Dist: scikit-learn
Requires-Dist: scipy
Requires-Dist: tqdm
